matplotlib_lossless_webp.py
matplotlib_lossless_webp-1.1.1.dist-info/LICENSE
matplotlib_lossless_webp-1.1.1.dist-info/METADATA
matplotlib_lossless_webp-1.1.1.dist-info/WHEEL
matplotlib_lossless_webp-1.1.1.dist-info/top_level.txt
matplotlib_lossless_webp-1.1.1.dist-info/RECORD
