Metadata-Version: 2.2
Name: matplotlib-lossless-webp
Version: 1.1.1
Summary: Tiny Python package that forces lossless compression in matplotlib when saving WebP images
Home-page: https://github.com/ragibson/matplotlib-lossless-webp
Author: Ryan Gibson
Author-email: ryan.alex.gibson@gmail.com
License: MIT
Keywords: matplotlib lossless webp
Classifier: Programming Language :: Python :: 3
Classifier: License :: OSI Approved :: MIT License
Classifier: Development Status :: 5 - Production/Stable
Classifier: Intended Audience :: Developers
Requires-Python: >=3.9
License-File: LICENSE
Requires-Dist: matplotlib
Dynamic: author
Dynamic: author-email
Dynamic: classifier
Dynamic: description
Dynamic: description-content-type
Dynamic: home-page
Dynamic: keywords
Dynamic: license
Dynamic: requires-dist
Dynamic: requires-python
Dynamic: summary
